{"level":{"size":{"w":512,"h":512},"tile_size":{"w":8,"h":8}},"tiles":[{"id":3923,"type":"Ground","ts":"testtiles19.png","pos":{"x":4,"y":116},"props":{}},{"id":3924,"type":"Ground","ts":"testtiles19.png","pos":{"x":12,"y":116},"props":{}},{"id":3925,"type":"Ground","ts":"testtiles19.png","pos":{"x":20,"y":116},"props":{}},{"id":3923,"type":"Ground","ts":"testtiles19.png","pos":{"x":28,"y":116},"props":{}},{"id":3924,"type":"Ground","ts":"testtiles19.png","pos":{"x":36,"y":116},"props":{}},{"id":3925,"type":"Ground","ts":"testtiles19.png","pos":{"x":44,"y":116},"props":{}},{"id":3923,"type":"Ground","ts":"testtiles19.png","pos":{"x":52,"y":116},"props":{}},{"id":3924,"type":"Ground","ts":"testtiles19.png","pos":{"x":60,"y":116},"props":{}},{"id":3925,"type":"Ground","ts":"testtiles19.png","pos":{"x":68,"y":116},"props":{}},{"id":3923,"type":"Ground","ts":"testtiles19.png","pos":{"x":100,"y":116},"props":{}},{"id":3924,"type":"Ground","ts":"testtiles19.png","pos":{"x":108,"y":116},"props":{}},{"id":3925,"type":"Ground","ts":"testtiles19.png","pos":{"x":116,"y":116},"props":{}},{"id":3923,"type":"Ground","ts":"testtiles19.png","pos":{"x":124,"y":116},"props":{}},{"id":3924,"type":"Ground","ts":"testtiles19.png","pos":{"x":132,"y":116},"props":{}},{"id":3925,"type":"Ground","ts":"testtiles19.png","pos":{"x":140,"y":116},"props":{}},{"id":3923,"type":"Ground","ts":"testtiles19.png","pos":{"x":148,"y":116},"props":{}},{"id":3924,"type":"Ground","ts":"testtiles19.png","pos":{"x":156,"y":116},"props":{}},{"id":3925,"type":"Ground","ts":"testtiles19.png","pos":{"x":164,"y":116},"props":{}},{"id":3923,"type":"Ground","ts":"testtiles19.png","pos":{"x":196,"y":116},"props":{}},{"id":3924,"type":"Ground","ts":"testtiles19.png","pos":{"x":204,"y":116},"props":{}},{"id":3925,"type":"Ground","ts":"testtiles19.png","pos":{"x":212,"y":116},"props":{}},{"id":3923,"type":"Ground","ts":"testtiles19.png","pos":{"x":220,"y":116},"props":{}},{"id":3924,"type":"Ground","ts":"testtiles19.png","pos":{"x":228,"y":116},"props":{}},{"id":3925,"type":"Ground","ts":"testtiles19.png","pos":{"x":236,"y":116},"props":{}},{"id":3923,"type":"Ground","ts":"testtiles19.png","pos":{"x":244,"y":116},"props":{}},{"id":3924,"type":"Ground","ts":"testtiles19.png","pos":{"x":252,"y":116},"props":{}},{"id":3925,"type":"Ground","ts":"testtiles19.png","pos":{"x":260,"y":116},"props":{}},{"id":3923,"type":"Ground","ts":"testtiles19.png","pos":{"x":292,"y":116},"props":{}},{"id":3924,"type":"Ground","ts":"testtiles19.png","pos":{"x":300,"y":116},"props":{}},{"id":3925,"type":"Ground","ts":"testtiles19.png","pos":{"x":308,"y":116},"props":{}},{"id":3923,"type":"Ground","ts":"testtiles19.png","pos":{"x":316,"y":116},"props":{}},{"id":3924,"type":"Ground","ts":"testtiles19.png","pos":{"x":324,"y":116},"props":{}},{"id":3925,"type":"Ground","ts":"testtiles19.png","pos":{"x":332,"y":116},"props":{}},{"id":3923,"type":"Ground","ts":"testtiles19.png","pos":{"x":340,"y":116},"props":{}},{"id":3924,"type":"Ground","ts":"testtiles19.png","pos":{"x":348,"y":116},"props":{}},{"id":3925,"type":"Ground","ts":"testtiles19.png","pos":{"x":356,"y":116},"props":{}},{"id":3923,"type":"Ground","ts":"testtiles19.png","pos":{"x":388,"y":116},"props":{}},{"id":3924,"type":"Ground","ts":"testtiles19.png","pos":{"x":396,"y":116},"props":{}},{"id":3925,"type":"Ground","ts":"testtiles19.png","pos":{"x":404,"y":116},"props":{}},{"id":3923,"type":"Ground","ts":"testtiles19.png","pos":{"x":412,"y":116},"props":{}},{"id":3924,"type":"Ground","ts":"testtiles19.png","pos":{"x":420,"y":116},"props":{}},{"id":3925,"type":"Ground","ts":"testtiles19.png","pos":{"x":428,"y":116},"props":{}},{"id":3923,"type":"Ground","ts":"testtiles19.png","pos":{"x":436,"y":116},"props":{}},{"id":3924,"type":"Ground","ts":"testtiles19.png","pos":{"x":444,"y":116},"props":{}},{"id":3925,"type":"Ground","ts":"testtiles19.png","pos":{"x":452,"y":116},"props":{}},{"id":3923,"type":"Ground","ts":"testtiles19.png","pos":{"x":484,"y":116},"props":{}},{"id":3924,"type":"Ground","ts":"testtiles19.png","pos":{"x":492,"y":116},"props":{}},{"id":3925,"type":"Ground","ts":"testtiles19.png","pos":{"x":500,"y":116},"props":{}},{"id":3923,"type":"Ground","ts":"testtiles19.png","pos":{"x":508,"y":116},"props":{}},{"id":3987,"type":"Ground","ts":"testtiles19.png","pos":{"x":4,"y":108},"props":{}},{"id":3988,"type":"Ground","ts":"testtiles19.png","pos":{"x":12,"y":108},"props":{}},{"id":3989,"type":"Ground","ts":"testtiles19.png","pos":{"x":20,"y":108},"props":{}},{"id":3987,"type":"Ground","ts":"testtiles19.png","pos":{"x":28,"y":108},"props":{}},{"id":3988,"type":"Ground","ts":"testtiles19.png","pos":{"x":36,"y":108},"props":{}},{"id":3989,"type":"Ground","ts":"testtiles19.png","pos":{"x":44,"y":108},"props":{}},{"id":3987,"type":"Ground","ts":"testtiles19.png","pos":{"x":52,"y":108},"props":{}},{"id":3988,"type":"Ground","ts":"testtiles19.png","pos":{"x":60,"y":108},"props":{}},{"id":3989,"type":"Ground","ts":"testtiles19.png","pos":{"x":68,"y":108},"props":{}},{"id":3987,"type":"Ground","ts":"testtiles19.png","pos":{"x":100,"y":108},"props":{}},{"id":3988,"type":"Ground","ts":"testtiles19.png","pos":{"x":108,"y":108},"props":{}},{"id":3989,"type":"Ground","ts":"testtiles19.png","pos":{"x":116,"y":108},"props":{}},{"id":3987,"type":"Ground","ts":"testtiles19.png","pos":{"x":124,"y":108},"props":{}},{"id":3988,"type":"Ground","ts":"testtiles19.png","pos":{"x":132,"y":108},"props":{}},{"id":3989,"type":"Ground","ts":"testtiles19.png","pos":{"x":140,"y":108},"props":{}},{"id":3987,"type":"Ground","ts":"testtiles19.png","pos":{"x":148,"y":108},"props":{}},{"id":3988,"type":"Ground","ts":"testtiles19.png","pos":{"x":156,"y":108},"props":{}},{"id":3989,"type":"Ground","ts":"testtiles19.png","pos":{"x":164,"y":108},"props":{}},{"id":3987,"type":"Ground","ts":"testtiles19.png","pos":{"x":196,"y":108},"props":{}},{"id":3988,"type":"Ground","ts":"testtiles19.png","pos":{"x":204,"y":108},"props":{}},{"id":3989,"type":"Ground","ts":"testtiles19.png","pos":{"x":212,"y":108},"props":{}},{"id":3987,"type":"Ground","ts":"testtiles19.png","pos":{"x":220,"y":108},"props":{}},{"id":3988,"type":"Ground","ts":"testtiles19.png","pos":{"x":228,"y":108},"props":{}},{"id":3989,"type":"Ground","ts":"testtiles19.png","pos":{"x":236,"y":108},"props":{}},{"id":3987,"type":"Ground","ts":"testtiles19.png","pos":{"x":244,"y":108},"props":{}},{"id":3988,"type":"Ground","ts":"testtiles19.png","pos":{"x":252,"y":108},"props":{}},{"id":3989,"type":"Ground","ts":"testtiles19.png","pos":{"x":260,"y":108},"props":{}},{"id":3987,"type":"Ground","ts":"testtiles19.png","pos":{"x":292,"y":108},"props":{}},{"id":3988,"type":"Ground","ts":"testtiles19.png","pos":{"x":300,"y":108},"props":{}},{"id":3989,"type":"Ground","ts":"testtiles19.png","pos":{"x":308,"y":108},"props":{}},{"id":3987,"type":"Ground","ts":"testtiles19.png","pos":{"x":316,"y":108},"props":{}},{"id":3988,"type":"Ground","ts":"testtiles19.png","pos":{"x":324,"y":108},"props":{}},{"id":3989,"type":"Ground","ts":"testtiles19.png","pos":{"x":332,"y":108},"props":{}},{"id":3987,"type":"Ground","ts":"testtiles19.png","pos":{"x":340,"y":108},"props":{}},{"id":3988,"type":"Ground","ts":"testtiles19.png","pos":{"x":348,"y":108},"props":{}},{"id":3989,"type":"Ground","ts":"testtiles19.png","pos":{"x":356,"y":108},"props":{}},{"id":3987,"type":"Ground","ts":"testtiles19.png","pos":{"x":388,"y":108},"props":{}},{"id":3988,"type":"Ground","ts":"testtiles19.png","pos":{"x":396,"y":108},"props":{}},{"id":3989,"type":"Ground","ts":"testtiles19.png","pos":{"x":404,"y":108},"props":{}},{"id":3987,"type":"Ground","ts":"testtiles19.png","pos":{"x":412,"y":108},"props":{}},{"id":3988,"type":"Ground","ts":"testtiles19.png","pos":{"x":420,"y":108},"props":{}},{"id":3989,"type":"Ground","ts":"testtiles19.png","pos":{"x":428,"y":108},"props":{}},{"id":3987,"type":"Ground","ts":"testtiles19.png","pos":{"x":436,"y":108},"props":{}},{"id":3988,"type":"Ground","ts":"testtiles19.png","pos":{"x":444,"y":108},"props":{}},{"id":3989,"type":"Ground","ts":"testtiles19.png","pos":{"x":452,"y":108},"props":{}},{"id":3987,"type":"Ground","ts":"testtiles19.png","pos":{"x":484,"y":108},"props":{}},{"id":3988,"type":"Ground","ts":"testtiles19.png","pos":{"x":492,"y":108},"props":{}},{"id":3989,"type":"Ground","ts":"testtiles19.png","pos":{"x":500,"y":108},"props":{}},{"id":3987,"type":"Ground","ts":"testtiles19.png","pos":{"x":508,"y":108},"props":{}},{"id":4051,"type":"Ground","ts":"testtiles19.png","pos":{"x":4,"y":100},"props":{}},{"id":4052,"type":"Ground","ts":"testtiles19.png","pos":{"x":12,"y":100},"props":{}},{"id":4053,"type":"Ground","ts":"testtiles19.png","pos":{"x":20,"y":100},"props":{}},{"id":4051,"type":"Ground","ts":"testtiles19.png","pos":{"x":28,"y":100},"props":{}},{"id":4052,"type":"Ground","ts":"testtiles19.png","pos":{"x":36,"y":100},"props":{}},{"id":4053,"type":"Ground","ts":"testtiles19.png","pos":{"x":44,"y":100},"props":{}},{"id":4051,"type":"Ground","ts":"testtiles19.png","pos":{"x":52,"y":100},"props":{}},{"id":4052,"type":"Ground","ts":"testtiles19.png","pos":{"x":60,"y":100},"props":{}},{"id":4053,"type":"Ground","ts":"testtiles19.png","pos":{"x":68,"y":100},"props":{}},{"id":4051,"type":"Ground","ts":"testtiles19.png","pos":{"x":100,"y":100},"props":{}},{"id":4052,"type":"Ground","ts":"testtiles19.png","pos":{"x":108,"y":100},"props":{}},{"id":4053,"type":"Ground","ts":"testtiles19.png","pos":{"x":116,"y":100},"props":{}},{"id":4051,"type":"Ground","ts":"testtiles19.png","pos":{"x":124,"y":100},"props":{}},{"id":4052,"type":"Ground","ts":"testtiles19.png","pos":{"x":132,"y":100},"props":{}},{"id":4053,"type":"Ground","ts":"testtiles19.png","pos":{"x":140,"y":100},"props":{}},{"id":4051,"type":"Ground","ts":"testtiles19.png","pos":{"x":148,"y":100},"props":{}},{"id":4052,"type":"Ground","ts":"testtiles19.png","pos":{"x":156,"y":100},"props":{}},{"id":4053,"type":"Ground","ts":"testtiles19.png","pos":{"x":164,"y":100},"props":{}},{"id":4051,"type":"Ground","ts":"testtiles19.png","pos":{"x":196,"y":100},"props":{}},{"id":4052,"type":"Ground","ts":"testtiles19.png","pos":{"x":204,"y":100},"props":{}},{"id":4053,"type":"Ground","ts":"testtiles19.png","pos":{"x":212,"y":100},"props":{}},{"id":4051,"type":"Ground","ts":"testtiles19.png","pos":{"x":220,"y":100},"props":{}},{"id":4052,"type":"Ground","ts":"testtiles19.png","pos":{"x":228,"y":100},"props":{}},{"id":4053,"type":"Ground","ts":"testtiles19.png","pos":{"x":236,"y":100},"props":{}},{"id":4051,"type":"Ground","ts":"testtiles19.png","pos":{"x":244,"y":100},"props":{}},{"id":4052,"type":"Ground","ts":"testtiles19.png","pos":{"x":252,"y":100},"props":{}},{"id":4053,"type":"Ground","ts":"testtiles19.png","pos":{"x":260,"y":100},"props":{}},{"id":4051,"type":"Ground","ts":"testtiles19.png","pos":{"x":292,"y":100},"props":{}},{"id":4052,"type":"Ground","ts":"testtiles19.png","pos":{"x":300,"y":100},"props":{}},{"id":4053,"type":"Ground","ts":"testtiles19.png","pos":{"x":308,"y":100},"props":{}},{"id":4051,"type":"Ground","ts":"testtiles19.png","pos":{"x":316,"y":100},"props":{}},{"id":4052,"type":"Ground","ts":"testtiles19.png","pos":{"x":324,"y":100},"props":{}},{"id":4053,"type":"Ground","ts":"testtiles19.png","pos":{"x":332,"y":100},"props":{}},{"id":4051,"type":"Ground","ts":"testtiles19.png","pos":{"x":340,"y":100},"props":{}},{"id":4052,"type":"Ground","ts":"testtiles19.png","pos":{"x":348,"y":100},"props":{}},{"id":4053,"type":"Ground","ts":"testtiles19.png","pos":{"x":356,"y":100},"props":{}},{"id":4051,"type":"Ground","ts":"testtiles19.png","pos":{"x":388,"y":100},"props":{}},{"id":4052,"type":"Ground","ts":"testtiles19.png","pos":{"x":396,"y":100},"props":{}},{"id":4053,"type":"Ground","ts":"testtiles19.png","pos":{"x":404,"y":100},"props":{}},{"id":4051,"type":"Ground","ts":"testtiles19.png","pos":{"x":412,"y":100},"props":{}},{"id":4052,"type":"Ground","ts":"testtiles19.png","pos":{"x":420,"y":100},"props":{}},{"id":4053,"type":"Ground","ts":"testtiles19.png","pos":{"x":428,"y":100},"props":{}},{"id":4051,"type":"Ground","ts":"testtiles19.png","pos":{"x":436,"y":100},"props":{}},{"id":4052,"type":"Ground","ts":"testtiles19.png","pos":{"x":444,"y":100},"props":{}},{"id":4053,"type":"Ground","ts":"testtiles19.png","pos":{"x":452,"y":100},"props":{}},{"id":4051,"type":"Ground","ts":"testtiles19.png","pos":{"x":484,"y":100},"props":{}},{"id":4052,"type":"Ground","ts":"testtiles19.png","pos":{"x":492,"y":100},"props":{}},{"id":4053,"type":"Ground","ts":"testtiles19.png","pos":{"x":500,"y":100},"props":{}},{"id":4051,"type":"Ground","ts":"testtiles19.png","pos":{"x":508,"y":100},"props":{}},{"id":3923,"type":"Ground","ts":"testtiles19.png","pos":{"x":148,"y":92},"props":{}},{"id":3924,"type":"Ground","ts":"testtiles19.png","pos":{"x":156,"y":92},"props":{}},{"id":3925,"type":"Ground","ts":"testtiles19.png","pos":{"x":164,"y":92},"props":{}},{"id":3923,"type":"Ground","ts":"testtiles19.png","pos":{"x":172,"y":92},"props":{}},{"id":3924,"type":"Ground","ts":"testtiles19.png","pos":{"x":180,"y":92},"props":{}},{"id":3925,"type":"Ground","ts":"testtiles19.png","pos":{"x":188,"y":92},"props":{}},{"id":3923,"type":"Ground","ts":"testtiles19.png","pos":{"x":196,"y":92},"props":{}},{"id":3924,"type":"Ground","ts":"testtiles19.png","pos":{"x":204,"y":92},"props":{}},{"id":3925,"type":"Ground","ts":"testtiles19.png","pos":{"x":212,"y":92},"props":{}},{"id":3923,"type":"Ground","ts":"testtiles19.png","pos":{"x":244,"y":92},"props":{}},{"id":3924,"type":"Ground","ts":"testtiles19.png","pos":{"x":252,"y":92},"props":{}},{"id":3925,"type":"Ground","ts":"testtiles19.png","pos":{"x":260,"y":92},"props":{}},{"id":3923,"type":"Ground","ts":"testtiles19.png","pos":{"x":268,"y":92},"props":{}},{"id":3924,"type":"Ground","ts":"testtiles19.png","pos":{"x":276,"y":92},"props":{}},{"id":3925,"type":"Ground","ts":"testtiles19.png","pos":{"x":284,"y":92},"props":{}},{"id":3923,"type":"Ground","ts":"testtiles19.png","pos":{"x":292,"y":92},"props":{}},{"id":3924,"type":"Ground","ts":"testtiles19.png","pos":{"x":300,"y":92},"props":{}},{"id":3925,"type":"Ground","ts":"testtiles19.png","pos":{"x":308,"y":92},"props":{}},{"id":3923,"type":"Ground","ts":"testtiles19.png","pos":{"x":340,"y":92},"props":{}},{"id":3924,"type":"Ground","ts":"testtiles19.png","pos":{"x":348,"y":92},"props":{}},{"id":3925,"type":"Ground","ts":"testtiles19.png","pos":{"x":356,"y":92},"props":{}},{"id":3923,"type":"Ground","ts":"testtiles19.png","pos":{"x":364,"y":92},"props":{}},{"id":3924,"type":"Ground","ts":"testtiles19.png","pos":{"x":372,"y":92},"props":{}},{"id":3925,"type":"Ground","ts":"testtiles19.png","pos":{"x":380,"y":92},"props":{}},{"id":3923,"type":"Ground","ts":"testtiles19.png","pos":{"x":388,"y":92},"props":{}},{"id":3924,"type":"Ground","ts":"testtiles19.png","pos":{"x":396,"y":92},"props":{}},{"id":3925,"type":"Ground","ts":"testtiles19.png","pos":{"x":404,"y":92},"props":{}},{"id":3923,"type":"Ground","ts":"testtiles19.png","pos":{"x":484,"y":92},"props":{}},{"id":3924,"type":"Ground","ts":"testtiles19.png","pos":{"x":492,"y":92},"props":{}},{"id":3925,"type":"Ground","ts":"testtiles19.png","pos":{"x":500,"y":92},"props":{}},{"id":3987,"type":"Ground","ts":"testtiles19.png","pos":{"x":148,"y":84},"props":{}},{"id":3988,"type":"Ground","ts":"testtiles19.png","pos":{"x":156,"y":84},"props":{}},{"id":3989,"type":"Ground","ts":"testtiles19.png","pos":{"x":164,"y":84},"props":{}},{"id":3987,"type":"Ground","ts":"testtiles19.png","pos":{"x":172,"y":84},"props":{}},{"id":3988,"type":"Ground","ts":"testtiles19.png","pos":{"x":180,"y":84},"props":{}},{"id":3989,"type":"Ground","ts":"testtiles19.png","pos":{"x":188,"y":84},"props":{}},{"id":3987,"type":"Ground","ts":"testtiles19.png","pos":{"x":196,"y":84},"props":{}},{"id":3988,"type":"Ground","ts":"testtiles19.png","pos":{"x":204,"y":84},"props":{}},{"id":3989,"type":"Ground","ts":"testtiles19.png","pos":{"x":212,"y":84},"props":{}},{"id":3987,"type":"Ground","ts":"testtiles19.png","pos":{"x":244,"y":84},"props":{}},{"id":3988,"type":"Ground","ts":"testtiles19.png","pos":{"x":252,"y":84},"props":{}},{"id":3989,"type":"Ground","ts":"testtiles19.png","pos":{"x":260,"y":84},"props":{}},{"id":3987,"type":"Ground","ts":"testtiles19.png","pos":{"x":268,"y":84},"props":{}},{"id":3988,"type":"Ground","ts":"testtiles19.png","pos":{"x":276,"y":84},"props":{}},{"id":3989,"type":"Ground","ts":"testtiles19.png","pos":{"x":284,"y":84},"props":{}},{"id":3987,"type":"Ground","ts":"testtiles19.png","pos":{"x":292,"y":84},"props":{}},{"id":3988,"type":"Ground","ts":"testtiles19.png","pos":{"x":300,"y":84},"props":{}},{"id":3989,"type":"Ground","ts":"testtiles19.png","pos":{"x":308,"y":84},"props":{}},{"id":3987,"type":"Ground","ts":"testtiles19.png","pos":{"x":340,"y":84},"props":{}},{"id":3988,"type":"Ground","ts":"testtiles19.png","pos":{"x":348,"y":84},"props":{}},{"id":3989,"type":"Ground","ts":"testtiles19.png","pos":{"x":356,"y":84},"props":{}},{"id":3987,"type":"Ground","ts":"testtiles19.png","pos":{"x":364,"y":84},"props":{}},{"id":3988,"type":"Ground","ts":"testtiles19.png","pos":{"x":372,"y":84},"props":{}},{"id":3989,"type":"Ground","ts":"testtiles19.png","pos":{"x":380,"y":84},"props":{}},{"id":3987,"type":"Ground","ts":"testtiles19.png","pos":{"x":388,"y":84},"props":{}},{"id":3988,"type":"Ground","ts":"testtiles19.png","pos":{"x":396,"y":84},"props":{}},{"id":3989,"type":"Ground","ts":"testtiles19.png","pos":{"x":404,"y":84},"props":{}},{"id":3987,"type":"Ground","ts":"testtiles19.png","pos":{"x":484,"y":84},"props":{}},{"id":3988,"type":"Ground","ts":"testtiles19.png","pos":{"x":492,"y":84},"props":{}},{"id":3989,"type":"Ground","ts":"testtiles19.png","pos":{"x":500,"y":84},"props":{}},{"id":4051,"type":"Ground","ts":"testtiles19.png","pos":{"x":148,"y":76},"props":{}},{"id":4052,"type":"Ground","ts":"testtiles19.png","pos":{"x":156,"y":76},"props":{}},{"id":4053,"type":"Ground","ts":"testtiles19.png","pos":{"x":164,"y":76},"props":{}},{"id":4051,"type":"Ground","ts":"testtiles19.png","pos":{"x":172,"y":76},"props":{}},{"id":4052,"type":"Ground","ts":"testtiles19.png","pos":{"x":180,"y":76},"props":{}},{"id":4053,"type":"Ground","ts":"testtiles19.png","pos":{"x":188,"y":76},"props":{}},{"id":4051,"type":"Ground","ts":"testtiles19.png","pos":{"x":196,"y":76},"props":{}},{"id":4052,"type":"Ground","ts":"testtiles19.png","pos":{"x":204,"y":76},"props":{}},{"id":4053,"type":"Ground","ts":"testtiles19.png","pos":{"x":212,"y":76},"props":{}},{"id":4051,"type":"Ground","ts":"testtiles19.png","pos":{"x":244,"y":76},"props":{}},{"id":4052,"type":"Ground","ts":"testtiles19.png","pos":{"x":252,"y":76},"props":{}},{"id":4053,"type":"Ground","ts":"testtiles19.png","pos":{"x":260,"y":76},"props":{}},{"id":4051,"type":"Ground","ts":"testtiles19.png","pos":{"x":268,"y":76},"props":{}},{"id":4052,"type":"Ground","ts":"testtiles19.png","pos":{"x":276,"y":76},"props":{}},{"id":4053,"type":"Ground","ts":"testtiles19.png","pos":{"x":284,"y":76},"props":{}},{"id":4051,"type":"Ground","ts":"testtiles19.png","pos":{"x":292,"y":76},"props":{}},{"id":4052,"type":"Ground","ts":"testtiles19.png","pos":{"x":300,"y":76},"props":{}},{"id":4053,"type":"Ground","ts":"testtiles19.png","pos":{"x":308,"y":76},"props":{}},{"id":4051,"type":"Ground","ts":"testtiles19.png","pos":{"x":340,"y":76},"props":{}},{"id":4052,"type":"Ground","ts":"testtiles19.png","pos":{"x":348,"y":76},"props":{}},{"id":4053,"type":"Ground","ts":"testtiles19.png","pos":{"x":356,"y":76},"props":{}},{"id":4051,"type":"Ground","ts":"testtiles19.png","pos":{"x":364,"y":76},"props":{}},{"id":4052,"type":"Ground","ts":"testtiles19.png","pos":{"x":372,"y":76},"props":{}},{"id":4053,"type":"Ground","ts":"testtiles19.png","pos":{"x":380,"y":76},"props":{}},{"id":4051,"type":"Ground","ts":"testtiles19.png","pos":{"x":388,"y":76},"props":{}},{"id":4052,"type":"Ground","ts":"testtiles19.png","pos":{"x":396,"y":76},"props":{}},{"id":4053,"type":"Ground","ts":"testtiles19.png","pos":{"x":404,"y":76},"props":{}},{"id":4051,"type":"Ground","ts":"testtiles19.png","pos":{"x":484,"y":76},"props":{}},{"id":4052,"type":"Ground","ts":"testtiles19.png","pos":{"x":492,"y":76},"props":{}},{"id":4053,"type":"Ground","ts":"testtiles19.png","pos":{"x":500,"y":76},"props":{}},{"id":3923,"type":"Ground","ts":"testtiles19.png","pos":{"x":484,"y":68},"props":{}},{"id":3924,"type":"Ground","ts":"testtiles19.png","pos":{"x":492,"y":68},"props":{}},{"id":3925,"type":"Ground","ts":"testtiles19.png","pos":{"x":500,"y":68},"props":{}},{"id":3987,"type":"Ground","ts":"testtiles19.png","pos":{"x":484,"y":60},"props":{}},{"id":3988,"type":"Ground","ts":"testtiles19.png","pos":{"x":492,"y":60},"props":{}},{"id":3989,"type":"Ground","ts":"testtiles19.png","pos":{"x":500,"y":60},"props":{}},{"id":4051,"type":"Ground","ts":"testtiles19.png","pos":{"x":484,"y":52},"props":{}},{"id":4052,"type":"Ground","ts":"testtiles19.png","pos":{"x":492,"y":52},"props":{}},{"id":4053,"type":"Ground","ts":"testtiles19.png","pos":{"x":500,"y":52},"props":{}},{"id":3923,"type":"Ground","ts":"testtiles19.png","pos":{"x":484,"y":44},"props":{}},{"id":3924,"type":"Ground","ts":"testtiles19.png","pos":{"x":492,"y":44},"props":{}},{"id":3925,"type":"Ground","ts":"testtiles19.png","pos":{"x":500,"y":44},"props":{}},{"id":3987,"type":"Ground","ts":"testtiles19.png","pos":{"x":484,"y":36},"props":{}},{"id":3988,"type":"Ground","ts":"testtiles19.png","pos":{"x":492,"y":36},"props":{}},{"id":3989,"type":"Ground","ts":"testtiles19.png","pos":{"x":500,"y":36},"props":{}},{"id":4051,"type":"Ground","ts":"testtiles19.png","pos":{"x":484,"y":28},"props":{}},{"id":4052,"type":"Ground","ts":"testtiles19.png","pos":{"x":492,"y":28},"props":{}},{"id":4053,"type":"Ground","ts":"testtiles19.png","pos":{"x":500,"y":28},"props":{}},{"id":3985,"type":"Ground","ts":"testtiles19.png","pos":{"x":220,"y":20},"props":{}},{"id":3986,"type":"Ground","ts":"testtiles19.png","pos":{"x":228,"y":20},"props":{}},{"id":3985,"type":"Ground","ts":"testtiles19.png","pos":{"x":284,"y":20},"props":{}},{"id":3986,"type":"Ground","ts":"testtiles19.png","pos":{"x":292,"y":20},"props":{}},{"id":3985,"type":"Ground","ts":"testtiles19.png","pos":{"x":348,"y":20},"props":{}},{"id":3986,"type":"Ground","ts":"testtiles19.png","pos":{"x":356,"y":20},"props":{}},{"id":3985,"type":"Ground","ts":"testtiles19.png","pos":{"x":412,"y":20},"props":{}},{"id":3986,"type":"Ground","ts":"testtiles19.png","pos":{"x":420,"y":20},"props":{}},{"id":3923,"type":"Ground","ts":"testtiles19.png","pos":{"x":460,"y":20},"props":{}},{"id":3924,"type":"Ground","ts":"testtiles19.png","pos":{"x":468,"y":20},"props":{}},{"id":3925,"type":"Ground","ts":"testtiles19.png","pos":{"x":476,"y":20},"props":{}},{"id":3923,"type":"Ground","ts":"testtiles19.png","pos":{"x":484,"y":20},"props":{}},{"id":3924,"type":"Ground","ts":"testtiles19.png","pos":{"x":492,"y":20},"props":{}},{"id":3925,"type":"Ground","ts":"testtiles19.png","pos":{"x":500,"y":20},"props":{}},{"id":4049,"type":"Ground","ts":"testtiles19.png","pos":{"x":220,"y":12},"props":{}},{"id":4050,"type":"Ground","ts":"testtiles19.png","pos":{"x":228,"y":12},"props":{}},{"id":4049,"type":"Ground","ts":"testtiles19.png","pos":{"x":284,"y":12},"props":{}},{"id":4050,"type":"Ground","ts":"testtiles19.png","pos":{"x":292,"y":12},"props":{}},{"id":4049,"type":"Ground","ts":"testtiles19.png","pos":{"x":348,"y":12},"props":{}},{"id":4050,"type":"Ground","ts":"testtiles19.png","pos":{"x":356,"y":12},"props":{}},{"id":4049,"type":"Ground","ts":"testtiles19.png","pos":{"x":412,"y":12},"props":{}},{"id":4050,"type":"Ground","ts":"testtiles19.png","pos":{"x":420,"y":12},"props":{}},{"id":3987,"type":"Ground","ts":"testtiles19.png","pos":{"x":460,"y":12},"props":{}},{"id":3988,"type":"Ground","ts":"testtiles19.png","pos":{"x":468,"y":12},"props":{}},{"id":3989,"type":"Ground","ts":"testtiles19.png","pos":{"x":476,"y":12},"props":{}},{"id":3987,"type":"Ground","ts":"testtiles19.png","pos":{"x":484,"y":12},"props":{}},{"id":3988,"type":"Ground","ts":"testtiles19.png","pos":{"x":492,"y":12},"props":{}},{"id":3989,"type":"Ground","ts":"testtiles19.png","pos":{"x":500,"y":12},"props":{}},{"id":4051,"type":"Ground","ts":"testtiles19.png","pos":{"x":460,"y":4},"props":{}},{"id":4052,"type":"Ground","ts":"testtiles19.png","pos":{"x":468,"y":4},"props":{}},{"id":4053,"type":"Ground","ts":"testtiles19.png","pos":{"x":476,"y":4},"props":{}},{"id":4051,"type":"Ground","ts":"testtiles19.png","pos":{"x":484,"y":4},"props":{}},{"id":4052,"type":"Ground","ts":"testtiles19.png","pos":{"x":492,"y":4},"props":{}},{"id":4053,"type":"Ground","ts":"testtiles19.png","pos":{"x":500,"y":4},"props":{}}],"objects":[{"type":{"Custom":"PushableBlock"},"pos":{"x":124,"y":132},"size":{"w":24,"h":24},"props":{}},{"type":{"Custom":"PushableBlock"},"pos":{"x":124,"y":156},"size":{"w":24,"h":24},"props":{}},{"type":{"Custom":"PushableBlock"},"pos":{"x":124,"y":180},"size":{"w":24,"h":24},"props":{}},{"type":{"Custom":"PushableBlock"},"pos":{"x":124,"y":204},"size":{"w":24,"h":24},"props":{}},{"type":"Player","pos":{"x":36,"y":156},"size":{"w":24,"h":40},"props":{}}]}